dcm/__init__.py
dcm/dcm.py
dcm/linear_interpolation.py
dcm/system_constants.py
dcm/typing.py
python_dcm-0.1.10.dist-info/METADATA
python_dcm-0.1.10.dist-info/WHEEL
python_dcm-0.1.10.dist-info/RECORD
