Metadata-Version: 2.1
Name: python-dcm
Version: 0.1.10
Summary: A high-performance Python package for handling ETAS DCM(Data Conversion Format) files used in engine calibration tools like INCA, MDA, EHANDBOOK, and CANape.
License: MIT
Author: c0sogi
Author-email: dcas@naver.com
Requires-Python: >=3.10
Classifier: License :: OSI Approved :: MIT License
Classifier: Programming Language :: Python :: 3
Classifier: Programming Language :: Python :: 3.10
Classifier: Programming Language :: Python :: 3.11
Classifier: Programming Language :: Python :: 3.12
Requires-Dist: matplotlib (>=3.0.0,<4)
Requires-Dist: numpy (>=1.20.0,<3)
Requires-Dist: openpyxl (>=3.1.0,<4.0.0)
Requires-Dist: pandas (>=1.5.0,<3)
